Metadata-Version: 2.1
Name: ExtreMods
Version: 2.5
Summary: A Secure  and Powerful Python-Telethon Based Library For ExtemePro Userbot.
Home-page: https://github.com/TeamExtremePro/ExtremeProUserbot
Author: AmanPandey
Author-email: paman7647@gmail.com
License: GNU AFFERO GENERAL PUBLIC LICENSE (v3)
Platform: UNKNOWN
Classifier: Programming Language :: Python :: 3
Classifier: License :: OSI Approved :: GNU General Public License v3 (GPLv3)
Classifier: Operating System :: OS Independent
Requires-Python: >=3.6
